grokcore.annotation-4.1-py3.12-nspkg.pth
grokcore/annotation/__init__.py
grokcore/annotation/components.py
grokcore/annotation/configure.zcml
grokcore/annotation/interfaces.py
grokcore/annotation/lazy.py
grokcore/annotation/meta.py
grokcore/annotation/meta.zcml
grokcore/annotation/testing.py
grokcore/annotation/tests/__init__.py
grokcore/annotation/tests/test_grok.py
grokcore/annotation/tests/annotation/__init__.py
grokcore/annotation/tests/annotation/annotation.py
grokcore/annotation/tests/annotation/implementsmany.py
grokcore/annotation/tests/annotation/implementsnone.py
grokcore/annotation/tests/annotation/lazy.py
grokcore/annotation/tests/annotation/name.py
grokcore/annotation/tests/annotation/provides.py
grokcore_annotation-4.1.dist-info/LICENSE.txt
grokcore_annotation-4.1.dist-info/METADATA
grokcore_annotation-4.1.dist-info/WHEEL
grokcore_annotation-4.1.dist-info/namespace_packages.txt
grokcore_annotation-4.1.dist-info/top_level.txt
grokcore_annotation-4.1.dist-info/RECORD
