Metadata-Version: 2.2
Name: grokcore.annotation
Version: 4.1
Summary: Grok-like configuration for Zope annotations
Home-page: https://github.com/zopefoundation/grokcore.annotation
Author: Grok Team
Author-email: zope-dev@zope.dev
License: ZPL-2.1
Classifier: Environment :: Web Environment
Classifier: Intended Audience :: Developers
Classifier: License :: OSI Approved :: Zope Public License
Classifier: Programming Language :: Python
Classifier: Programming Language :: Python :: 3
Classifier: Programming Language :: Python :: 3.9
Classifier: Programming Language :: Python :: 3.10
Classifier: Programming Language :: Python :: 3.11
Classifier: Programming Language :: Python :: 3.12
Classifier: Programming Language :: Python :: 3.13
Classifier: Programming Language :: Python :: Implementation :: CPython
Classifier: Programming Language :: Python :: Implementation :: PyPy
Classifier: Framework :: Zope :: 3
Requires-Python: >=3.9
License-File: LICENSE.txt
Requires-Dist: grokcore.component>=2.5
Requires-Dist: martian
Requires-Dist: setuptools
Requires-Dist: zope.annotation
Requires-Dist: zope.cachedescriptors
Requires-Dist: zope.component
Requires-Dist: zope.container
Requires-Dist: zope.event
Requires-Dist: zope.interface
Requires-Dist: zope.location
Requires-Dist: zope.schema
Provides-Extra: test
Requires-Dist: zope.configuration; extra == "test"
Requires-Dist: zope.schema; extra == "test"
Requires-Dist: zope.testing>4.6; extra == "test"
Requires-Dist: zope.testrunner; extra == "test"
Dynamic: author
Dynamic: author-email
Dynamic: classifier
Dynamic: description
Dynamic: home-page
Dynamic: license
Dynamic: provides-extra
Dynamic: requires-dist
Dynamic: requires-python
Dynamic: summary
